mpdx/__init__.py
mpdx/__version__.py
mpdx/canonical_table.py
mpdx/document.py
mpdx/html_ctl_converter.py
mpdx/kan.py
mpdx/mpdx_to_html.py
mpdx/mpis.py
mpdx/node.py
mpdx/parser.py
mpdx/convert/ctl_to_mpdx.py
mpdx/convert/mpdx_to_ctl.py
mpdx/io/__init__.py
mpdx/io/docx.py
mpdx/io/html.py
mpdx/io/md.py
mpdx/layout/ctl.py
mpdx/layout/parser.py
mpdx-0.1.0a1.dist-info/METADATA
mpdx-0.1.0a1.dist-info/WHEEL
mpdx-0.1.0a1.dist-info/top_level.txt
mpdx-0.1.0a1.dist-info/RECORD
