Metadata-Version: 2.4
Name: mpdx
Version: 0.1.0a1
Summary: Semantic, graph-based document data model for text and tables
Author: MPDX Contributors
License-Expression: MIT
Requires-Python: >=3.9
